{
    "$schema": "https://schema.management.azure.com/schemas/2019-04-01/deploymentParameters.json#",
    "contentVersion": "1.0.0.0",
    "parameters": {
        "environmentType": {
            "value": "nonprod"
        },
        "postgreSQLServerName": {
            "value": "zaltayan-dbsrv-uat"
        },
        "postgreSQLDatabaseName": {
            "value": "zaltayan-db-uat"
        },
        "appServicePlanName": {
            "value": "zaltayan-asp-uat"
        },
        "appServiceAPIAppName": {
            "value": "zaltayan-be-uat"
        },
        "appServiceAppName": {
            "value": "zaltayan-fe-uat"
        },
        "location": {
            "value": "North Europe"
        }
    }
}